matrixmania/__init__.py
matrixmania/compute2.py
matrixmania_mg284_12345-0.2.3.dist-info/METADATA
matrixmania_mg284_12345-0.2.3.dist-info/WHEEL
matrixmania_mg284_12345-0.2.3.dist-info/RECORD
