Metadata-Version: 2.4
Name: matrixmania_mg284_12345
Version: 0.2.3
Summary: MatrixMania: Simple linear algebra functions for teaching (matmul, transpose, rot_2D).
Author-email: mg284 <grochme97696@th-nuernberg.de>
License: MIT
Requires-Python: >=3.7
Requires-Dist: tabulate
